{"adult":false,"backdrop_path":"/n2aX63BmW7zIKgKJ58e6rKlSsdi.jpg","belongs_to_collection":null,"budget":21000000,"genres":[{"id":"53","name":"Thriller"},{"id":"9648","name":"Mystery"},{"id":"27","name":"Horror"}],"homepage":"http://petsematarymovie.com","id":"157433","imdb_id":"tt0837563","original_language":"en","original_title":"Pet Sematary","overview":"Louis Creed, his wife Rachel and their two children Gage and Ellie move to a rural home where they are welcomed and enlightened about the eerie 'Pet Sematary' located nearby. After the tragedy of their cat being killed by a truck, Louis resorts to burying it in the mysterious pet cemetery, which is definitely not as it seems, as it proves to the Creeds that sometimes dead is better.","popularity":113.053,"poster_path":"/7SPhr7Qj39vbnfF9O2qHRYaKHAL.jpg","production_companies":[{"id":"435","logo_path":null,"name":"Di Bonaventura Pictures","origin_country":"US"},{"id":"11462","logo_path":"/7ZymELJwuWR4k5p0oeZ3d3WAhO3.png","name":"Alphaville Films","origin_country":""},{"id":"4","logo_path":"/fycMZt242LVjagMByZOLUGbCvv3.png","name":"Paramount","origin_country":"US"},{"id":"6302","logo_path":null,"name":"Room 101","origin_country":""}],"production_countries":[{"iso_3166_1":"US","name":"United States of America"}],"release_date":"2019-04-04","revenue":109589957,"runtime":101,"spoken_languages":[{"iso_639_1":"en","name":"English"}],"status":"Released","tagline":"Sometimes dead Is better","title":"Pet Sematary","video":false,"vote_average":5.9,"vote_count":540,"videos":{"results":[{"id":"5c60060c0e0a2638236b70f5","iso_639_1":"en","iso_3166_1":"US","key":"VllcgXSIJkE","name":"Pet Sematary (2019)- Official Trailer- Paramount Pictures","site":"YouTube","size":1080,"type":"Trailer"},{"id":"5c600613c3a368386c87414b","iso_639_1":"en","iso_3166_1":"US","key":"zK0LNzU2TQI","name":"Pet Sematary (2019) - Trailer 2 - Paramount Pictures","site":"YouTube","size":1080,"type":"Trailer"},{"id":"5c9507dd0e0a2645eb5073a0","iso_639_1":"en","iso_3166_1":"US","key":"sI6vNp9evt8","name":"Pet Sematary (2019)- Dead Digital - Paramount Pictures","site":"YouTube","size":1080,"type":"Teaser"},{"id":"5c9507e99251417303762d1d","iso_639_1":"en","iso_3166_1":"US","key":"ivvHLJaRnQU","name":"Pet Sematary (2019) - True Horror Featurette - Paramount Pictures","site":"YouTube","size":1080,"type":"Featurette"},{"id":"5c9507fb925141731e761f45","iso_639_1":"en","iso_3166_1":"US","key":"gEUFh-Pv1nc","name":"Pet Sematary (2019)- Hug Your Daughter - Paramount Pictures","site":"YouTube","size":1080,"type":"Clip"},{"id":"5ca2d9cec3a3682b2a104c93","iso_639_1":"en","iso_3166_1":"US","key":"XakmsXltPkA","name":"Pet Sematary (2019) - Final Trailer - Paramount Pictures","site":"YouTube","size":1080,"type":"Trailer"}]}}
